{
  "appPageId" : "eebed06f-6914-44c1-a5eb-c71d60a64035",
  "componentName" : "siteforce:sldsOneColLayout",
  "id" : "c979f036-34da-4f84-8387-963a35f00466",
  "label" : "Resources",
  "regions" : [ {
    "id" : "3ccf1088-32fc-40c0-9055-2d202b38b4ec",
    "regionName" : "header",
    "type" : "region"
  }, {
    "components" : [ {
      "componentAttributes" : {
        "pageSize" : 25
      },
      "componentName" : "forceCommunity:filesList",
      "id" : "68ae4ec5-2d00-4a19-9853-97d82e02a6bb",
      "renderPriority" : "NEUTRAL",
      "renditionMap" : { },
      "type" : "component"
    } ],
    "id" : "a5f447ad-2c5a-4661-b416-063e034e3b7f",
    "regionName" : "content",
    "type" : "region"
  }, {
    "id" : "8d1e162e-d7f4-43af-a38a-8a9b62ac9a54",
    "regionName" : "footer",
    "type" : "region"
  }, {
    "components" : [ {
      "componentAttributes" : {
        "customHeadTags" : "",
        "description" : "",
        "title" : "Resources"
      },
      "componentName" : "forceCommunity:seoAssistant",
      "id" : "cfb3fb7e-dd2a-4b3a-92a7-e24e66ff68b1",
      "renditionMap" : { },
      "type" : "component"
    } ],
    "id" : "dfc4497a-94c4-455c-a092-36e7debed433",
    "regionName" : "sfdcHiddenRegion",
    "type" : "region"
  } ],
  "themeLayoutType" : "Inner",
  "type" : "view",
  "viewType" : "files"
}