{
  "appPageId" : "eebed06f-6914-44c1-a5eb-c71d60a64035",
  "componentName" : "siteforce:sldsOneColLayout",
  "id" : "cc5acb47-9d1c-4ba6-9edc-a02c8944f82d",
  "label" : "Top Articles",
  "regions" : [ {
    "id" : "affd05a0-d7a5-4c4a-adba-02992fccefe7",
    "regionName" : "header",
    "type" : "region"
  }, {
    "components" : [ {
      "componentAttributes" : {
        "numberOfArticles" : 5,
        "showTitle" : true,
        "title" : "Top Articles",
        "topicList" : [ ]
      },
      "componentName" : "forceCommunity:topArticleList",
      "id" : "1266c923-f4f4-45e1-b748-4e95df8dfca1",
      "renderPriority" : "NEUTRAL",
      "renditionMap" : { },
      "type" : "component"
    } ],
    "id" : "f6e5e991-fa4b-4484-ac9d-30feb2e3a175",
    "regionName" : "content",
    "type" : "region"
  }, {
    "id" : "2774eeeb-9bba-4ba2-99c3-e5c490f6c772",
    "regionName" : "footer",
    "type" : "region"
  }, {
    "components" : [ {
      "componentAttributes" : {
        "customHeadTags" : "",
        "description" : "",
        "title" : "Top Articles"
      },
      "componentName" : "forceCommunity:seoAssistant",
      "id" : "903196d4-9224-43dc-966b-c520af487a53",
      "renditionMap" : { },
      "type" : "component"
    } ],
    "id" : "97642bc6-b0d8-4e80-a0e0-ae0cf769b4d9",
    "regionName" : "sfdcHiddenRegion",
    "type" : "region"
  } ],
  "themeLayoutType" : "Inner",
  "type" : "view",
  "viewType" : "top-articles"
}