{
  "appPageId" : "eebed06f-6914-44c1-a5eb-c71d60a64035",
  "componentName" : "siteforce:sldsOneColLayout",
  "id" : "e2b07b5c-a0e5-4515-8a92-1d783ffb366c",
  "label" : "Topic Catalog",
  "regions" : [ {
    "components" : [ {
      "componentAttributes" : {
        "bannerText" : "",
        "bannerTextWithKnowledge" : "Explore other <a href=\"javascript:void(0)\" class=\"headlineArticles\">articles</a> and <a href=\"javascript:void(0)\" class=\"headlineDiscussions\">discussions</a> on this topic.",
        "bannerTextWithoutKnowledge" : "Explore other <a href=\"javascript:void(0)\" class=\"headlineDiscussions\">discussions</a> on this topic.",
        "pageType" : "",
        "showSubTopics" : true,
        "title" : "Topics",
        "uniqueNameOrId" : ""
      },
      "componentName" : "forceCommunity:headline",
      "id" : "1e3f2ccb-43ab-4ee6-8a76-ef0478e292dc",
      "renderPriority" : "NEUTRAL",
      "renditionMap" : { },
      "type" : "component"
    } ],
    "id" : "f425bb91-07d8-4025-ab04-750f887ec44e",
    "regionName" : "header",
    "type" : "region"
  }, {
    "components" : [ {
      "componentAttributes" : { },
      "componentName" : "forceCommunity:topicCatalog",
      "id" : "8b92cb5a-025a-47fe-912b-3ce2f7fa0bcf",
      "renderPriority" : "NEUTRAL",
      "renditionMap" : { },
      "type" : "component"
    } ],
    "id" : "619c7dd0-02cb-44d0-96c1-8ee8feb8d29d",
    "regionName" : "content",
    "type" : "region"
  }, {
    "id" : "baec41d0-7586-4c3c-bd7b-2faa22e2d3c3",
    "regionName" : "footer",
    "type" : "region"
  }, {
    "components" : [ {
      "componentAttributes" : {
        "customHeadTags" : "",
        "description" : "",
        "title" : "Topic Catalog"
      },
      "componentName" : "forceCommunity:seoAssistant",
      "id" : "e08e8719-ac47-4124-b132-efd168044356",
      "renditionMap" : { },
      "type" : "component"
    } ],
    "id" : "00e5bdb8-5cd9-4ed5-b911-f0c5b0fef16e",
    "regionName" : "sfdcHiddenRegion",
    "type" : "region"
  } ],
  "themeLayoutType" : "Inner",
  "type" : "view",
  "viewType" : "topic-catalog"
}